peter_69/__init__.py
peter_69/peter_69.py
peter_69-0.1.4.dist-info/LICENSE.md
peter_69-0.1.4.dist-info/METADATA
peter_69-0.1.4.dist-info/WHEEL
peter_69-0.1.4.dist-info/top_level.txt
peter_69-0.1.4.dist-info/RECORD
