Metadata-Version: 2.1
Name: peter-69
Version: 0.1.4
Summary: A small demo library that describes the input number through PeTeR.
Home-page: https://peter-69.readthedocs.io/
Author: Reuben Devanesan
Author-email: reubendevanesan@gmail.com
License: MIT
Platform: UNKNOWN
Classifier: Intended Audience :: Developers
Classifier: License :: OSI Approved :: MIT License
Classifier: Programming Language :: Python
Classifier: Programming Language :: Python :: 3
Classifier: Programming Language :: Python :: 3.9
Classifier: Operating System :: OS Independent
License-File: LICENSE.md
Requires-Dist: numpy
